{"cameraMode":{"drawMode":0,"name":"Shaded","section":"Shading Mode"},"sceneLighting":true,"audioPlay":false,"sceneViewState":{"m_AlwaysRefresh":false,"showFog":true,"showSkybox":true,"showFlares":true,"showImageEffects":true,"showParticleSystems":true,"showVisualEffectGraphs":true,"m_FxEnabled":true},"in2DMode":false,"pivot":{"x":-0.8272953033447266,"y":3.2683887481689455,"z":31.090213775634767},"rotation":{"x":0.31349143385887148,"y":0.45045945048332217,"z":-0.1726481169462204,"w":0.8179454207420349},"size":15.561041831970215,"orthographic":false}